textstats.py
textstats-0.1.2.dist-info/WHEEL
textstats-0.1.2.dist-info/METADATA
textstats-0.1.2.dist-info/RECORD
